freesms/__init__.py
freesms/py.typed
freesms-0.3.0.dist-info/LICENSE
freesms-0.3.0.dist-info/METADATA
freesms-0.3.0.dist-info/WHEEL
freesms-0.3.0.dist-info/RECORD
