Metadata-Version: 2.3
Name: freesms
Version: 0.3.0
Summary: Send SMSes with Free Mobile
License: MIT
Keywords: free,free-mobile,sms
Author: Baptiste Fontaine
Author-email: b@ptistefontaine.fr
Requires-Python: >=3.8
Classifier: License :: OSI Approved :: MIT License
Classifier: Development Status :: 5 - Production/Stable
Classifier: Programming Language :: Python :: 3
Requires-Dist: requests (>=2.32.3,<3.0.0)
